loggerplus/__init__.py
loggerplus/__main__.py
loggerplus-0.1.3.dist-info/LICENSE
loggerplus-0.1.3.dist-info/METADATA
loggerplus-0.1.3.dist-info/WHEEL
loggerplus-0.1.3.dist-info/top_level.txt
loggerplus-0.1.3.dist-info/RECORD
