Metadata-Version: 2.1
Name: loggerplus
Version: 0.1.3
Summary: A wrapper around the Python logging module that provides a more flexible and powerful logging solution.
Home-page: https://github.com/th3w1zard1/LoggerPlus
Author: Benjamin Auquite
Author-email: Benjamin Auquite <halomastar@gmail.com>
License: GNU LESSER GENERAL PUBLIC LICENSE
Project-URL: Homepage, https://github.com/th3w1zard1/LoggerPlus
Project-URL: Documentation, https://github.com/th3w1zard1/LoggerPlus/blob/master/README.md
Project-URL: Repository, https://github.com/th3w1zard1/LoggerPlus.git
Project-URL: Issues, https://github.com/th3w1zard1/LoggerPlus/issues
Classifier: Programming Language :: Python :: 3
Classifier: License :: OSI Approved :: GNU Lesser General Public License v2 (LGPLv2)
Classifier: Operating System :: OS Independent
Requires-Python: >=3.8
License-File: LICENSE
Provides-Extra: color
Requires-Dist: colorama; extra == "color"
